LICENSE
README.md
setup.py
rpi_ws281x_disk/__init__.py
rpi_ws281x_disk/rpi_ws281x_disk.py
rpi_ws281x_disk.egg-info/PKG-INFO
rpi_ws281x_disk.egg-info/SOURCES.txt
rpi_ws281x_disk.egg-info/dependency_links.txt
rpi_ws281x_disk.egg-info/requires.txt
rpi_ws281x_disk.egg-info/top_level.txt
rpi_ws281x_disk/devicemaps/241led9ringRGB.json
rpi_ws281x_disk/devicemaps/__init__.py